{
  "main": {
    "id": "2bda0edae1ae249c",
    "type": "split",
    "children": [
      {
        "id": "92d323ddc750b447",
        "type": "tabs",
        "children": [
          {
            "id": "960fa16d553823d5",
            "type": "leaf",
            "state": {
              "type": "markdown",
              "state": {
                "file": "README.md",
                "mode": "source",
                "source": false
              }
            }
          }
        ]
      }
    ],
    "direction": "vertical"
  },
  "left": {
    "id": "43a5062b5815c4df",
    "type": "split",
    "children": [
      {
        "id": "dc18270cebae16a1",
        "type": "tabs",
        "children": [
          {
            "id": "3e01a6fabb37f56f",
            "type": "leaf",
            "state": {
              "type": "file-explorer",
              "state": {
                "sortOrder": "alphabetical"
              }
            }
          },
          {
            "id": "19000068b9a7e418",
            "type": "leaf",
            "state": {
              "type": "search",
              "state": {
                "query": "transaction",
                "matchingCase": false,
                "explainSearch": false,
                "collapseAll": false,
                "extraContext": false,
                "sortOrder": "alphabetical"
              }
            }
          },
          {
            "id": "f0791a2a895ea2d6",
            "type": "leaf",
            "state": {
              "type": "starred",
              "state": {}
            }
          }
        ]
      }
    ],
    "direction": "horizontal",
    "width": 418.5
  },
  "right": {
    "id": "c81351c154d9a15b",
    "type": "split",
    "children": [
      {
        "id": "d7ed26a08b5e0c15",
        "type": "tabs",
        "children": [
          {
            "id": "3f4d8285590993de",
            "type": "leaf",
            "state": {
              "type": "backlink",
              "state": {
                "file": "README.md",
                "collapseAll": false,
                "extraContext": false,
                "sortOrder": "alphabetical",
                "showSearch": false,
                "searchQuery": "",
                "backlinkCollapsed": false,
                "unlinkedCollapsed": true
              }
            }
          },
          {
            "id": "051986eecfb30aed",
            "type": "leaf",
            "state": {
              "type": "outgoing-link",
              "state": {
                "file": "README.md",
                "linksCollapsed": false,
                "unlinkedCollapsed": true
              }
            }
          },
          {
            "id": "0f6346be3afdd2e6",
            "type": "leaf",
            "state": {
              "type": "tag",
              "state": {
                "sortOrder": "frequency",
                "useHierarchy": true
              }
            }
          },
          {
            "id": "5907f50a76767c9c",
            "type": "leaf",
            "state": {
              "type": "outline",
              "state": {
                "file": "README.md"
              }
            }
          }
        ]
      }
    ],
    "direction": "horizontal",
    "width": 300,
    "collapsed": true
  },
  "left-ribbon": {
    "hiddenItems": {
      "switcher:Open quick switcher": false,
      "graph:Open graph view": false,
      "canvas:Create new canvas": false,
      "daily-notes:Open today's daily note": false,
      "templates:Insert template": false,
      "command-palette:Open command palette": false
    }
  },
  "active": "960fa16d553823d5",
  "lastOpenFiles": [
    "assets/images/backend/Pasted image 20230321233022.png",
    "assets/images/backend/Pasted image 20230325000240.png",
    "assets/images/backend/The-Physical-Layer-in-OSI-Model-Explained-thumbnail.jpeg",
    "assets/images/backend/Screen Shot 2023-03-29 at 8.38.54 PM.png",
    "assets/images/backend/Screen Shot 2023-03-28 at 12.02.17 AM 1.png",
    "assets/images/backend/Screen Shot 2023-03-27 at 9.41.27 PM.png",
    "assets/images/backend/Screen Shot 2023-03-28 at 12.02.17 AM.png",
    "assets/images/backend/Screen Shot 2023-03-21 at 1.19.50 AM.png",
    "assets/images/backend/Screen Shot 2023-03-20 at 11.32.08 PM.png",
    "assets/images/backend/Screen Shot 2023-03-27 at 9.41.16 PM.png",
    "assets/images/backend/Pasted image 20230329221836.png",
    "Areas/Programming/Backend/Design/Fundamentals of Backend Design Course/Protocols.md",
    "Areas/Programming/Backend/Design/Fundamentals of Backend Design Course/Further Studying.md",
    "Areas/Programming/Backend/Design/Fundamentals of Backend Design Course/Backend Communication Design Patterns.md",
    "README.md",
    "assets/images/postgres/migrations",
    "assets/images/postgres/internals",
    "assets/images/postgres/security",
    "assets/images/postgres/overview",
    "assets/images/postgres/testing",
    "assets/images/postgres/views",
    "Areas/Programming/Backend/Databases/Postgres/Design/Design.md",
    "Areas/Programming/Backend/Databases/Postgres/Design",
    "Areas/Programming/Backend/Databases/Postgres/Client Interfaces/Data Access Patterns.md",
    "Areas/Programming/Backend/Databases/Postgres/Client Interfaces/Client Interaction.md",
    "Areas/Programming/Backend/Databases/Postgres/The SQL Language/Full Text Search/Overview.md",
    "Areas/Programming/Backend/Databases/Postgres/The SQL Language/Full Text Search/Full Text Search.md",
    "Areas/Programming/Backend/Databases/Postgres/The SQL Language/Full Text Search",
    "Areas/Programming/Backend/Databases/Postgres/Client Interfaces/Index.md",
    "Areas/Programming/Backend/Databases/Postgres/Client Interfaces",
    "Resources/Programming/TCP.md",
    "Resources/Programming/Long Polling vs WebSockets vs SSE.md",
    "Resources/Programming/Multiplexing - Demultiplexing.md",
    "Resources/Programming/AVX.md",
    "Resources/Programming/Virtual Functions.md",
    "Areas/Programming/Backend/Databases/Postgres/Server Administration/Vacuum.md",
    "Areas/Programming/Backend/Databases/Postgres/Server Administration/Testing.md",
    "Areas/Programming/Backend/Databases/Postgres/Server Administration/Prepared Statements.md",
    "Resources/Programming/Locality of Reference.md",
    "Areas/Programming/Backend/Databases/Postgres/Server Administration/Reliability and WAL.md",
    "Areas/Programming/Backend/Databases/Postgres/The SQL Language/Performance Tips/Overview.md",
    "Areas/Programming/Backend/Databases/Postgres/The SQL Language/Indexes/Overview.md",
    "Areas/Programming/Backend/Databases/Postgres/The SQL Language/Queries/Overview.md",
    "Areas/Programming/Backend/Databases/Postgres/The SQL Language/Overview.md",
    "Areas/Programming/Backend/Databases/Postgres/The SQL Language/Data Manipulation/Overview.md",
    "assets/images/postgres/queries/009_-_joins_-_cheatsheet.pdf"
  ]
}